Workbook

Sheet 0. Notice
B2: Questionnaire d'évaluation de maturité — Gestion des risques et résilience
B3: Référentiel adapté de : OECD (2021), Enterprise Risk Management Maturity Model — étendu aux dimensions Continuité d'activité, Gestion de crise et Résilience organisationnelle (ISO 22301 / 22361 / 22316).
B5: Fiche d'identité de l'entité évaluée
B6: Nom de l'entité
B7: Secteur d'activité
B8: Effectif
B9: Périmètre évalué
B10: Personne référente
B11: Fonction
B12: Date de l'évaluation
B14: Mode d'emploi
B15: 1. Rendez-vous sur l'onglet « 1. Questionnaire ». Il comporte 22 affirmations réparties sur 11 dimensions (2 par dimension).
... B21: Comment choisir la modalité
B22: Modalité | C22: Points | D22: À retenir
B23: Non | C23: 0 | D23: La pratique décrite n'existe pas, ou seulement de façon informelle et non reproductible.
B24: Partiellement | C24: 1 | D24: La pratique existe mais sur une partie du périmètre seulement, ou de façon irrégulière, ou sans preuve d'efficacité (non testée, non mesurée, non suivie).
B25: Oui | C25: 2 | D25: La pratique est en place sur tout le périmètre, appliquée régulièrement, et son efficacité est démontrable.
B28: Barème de maturité par dimension
B29: Chaque dimension comporte 2 affirmations, soit 0 à 4 points. Chaque total correspond à un niveau de maturité.
B30: Points | C30: Taux | D30: Niveau | E30: Combinaison correspondante
B31: 0 | C31: 0 % | D31: Émergent | E31: Non + Non
B32: 1 | C32: 25 % | D32: En progression | E32: Non + Partiellement
B33: 2 | C33: 50 % | D33: Établi | E33: Non + Oui, ou Partiellement + Partiellement
B34: 3 | C34: 75 % | D34: Avancé | E34: Partiellement + Oui
B35: 4 | C35: 100 % | D35: Aspirationnel | E35: Oui + Oui
B38: Pondération des dimensions
B39: Poids modifiables (cellules jaunes). Le score global est la moyenne pondérée des taux de maturité par dimension.
B40: Dimension | C40: Poids
B41: 1. Stratégie | C41: 8
B42: 2. Gouvernance | C42: 12
B43: 3. Culture | C43: 8
B44: 4. Identification des risques | C44: 10
B45: 5. Analyse et évaluation des risques | C45: 10
B46: 6. Traitement des risques | C46: 10
B47: 7. Revue et révision | C47: 7
B48: 8. Information et reporting | C48: 7
B49: 9. Continuité d'activité (PCA/PRA) | C49: 12
B50: 10. Gestion de crise (PGC) | C50: 10
B51: 11. Résilience organisationnelle | C51: 6
B52: Total | C52: =SUM(C41:C51) -> 100

Sheet 1. Questionnaire
A1: Questionnaire — pour chaque affirmation, sélectionnez Non, Partiellement ou Oui
A2: « Partiellement » = pratique partielle, irrégulière, ou sans preuve d'efficacité. Voir l'onglet Notice.
A4: Dimension | B4: N° | C4: Affirmation | D4: Réponse | E4: Points | F4: Commentaire / preuve
A5: 1. Stratégie | B5: 1.1 | C5: Notre stratégie et nos objectifs annuels sont élaborés à partir d'une analyse formalisée des risques susceptibles d'en compromettre l'atteinte, et cette analyse est mise à jour à chaque cycle de planification. | E5: =IF(D5="","",MATCH(D5,{"Non";"Partiellement";"Oui"},0)-1)
B6: 1.2 | C6: Notre appétit au risque est formalisé dans un document validé par la direction générale, décliné en tolérances par domaine, et effectivement utilisé lors des arbitrages budgétaires et d'investissement. | E6: =IF(D6="","",MATCH(D6,{"Non";"Partiellement";"Oui"},0)-1)
A7: 2. Gouvernance | B7: 2.1 | C7: Une instance transverse dédiée aux risques se réunit selon une fréquence définie, dispose d'un mandat écrit | E7: =IF(D7="","",MATCH(D7,{"Non";"Partiellement";"Oui"},0)-1)
B8: 2.2 | C8: Les rôles, responsabilités et niveaux de délégation en matière de risques sont documentés et appliqués | E8: =IF(D8="","",MATCH(D8,{"Non";"Partiellement";"Oui"},0)-1)
A9: 3. Culture | B9: 3.1 | C9: La direction générale encourage explicitement et régulièrement les formatons et les sensibilisation en matière de gestion des risques | E9: =IF(D9="","",MATCH(D9,{"Non";"Partiellement";"Oui"},0)-1)
B10: 3.2 | C10: Tout collaborateur peut remonter un risque ou une alerte via un canal identifié et connu, sans crainte de conséquence personnelle | E10: =IF(D10="","",MATCH(D10,{"Non";"Partiellement";"Oui"},0)-1)
A11: 4. Identification des risques | B11: 4.1 | C11: Nous identifions nos risques à intervalles réguliers selon une méthode et une taxonomie communes à toutes les entités, et les résultats sont consolidés dans une cartographie validée par la gouvernance. | E11: =IF(D11="","",MATCH(D11,{"Non";"Partiellement";"Oui"},0)-1)
B12: 4.2 | C12: Nous organisons une veille sur les risques émergents dont les conclusions sont présentées à la gouvernance et alimentent formellement la révision de notre cartographie des risques. | E12: =IF(D12="","",MATCH(D12,{"Non";"Partiellement";"Oui"},0)-1)
A13: 5. Analyse et évaluation des risques | B13: 5.1 | C13: Nous évaluons nos risques selon une échelle unique dont les seuils sont calibrés par des repères chiffrés, appliquée de façon homogène dans toutes les entités. | E13: =IF(D13="","",MATCH(D13,{"Non";"Partiellement";"Oui"},0)-1)
B14: 5.2 | C14: Nous distinguons systématiquement le risque brut du risque résiduel après contrôles avec escalade en cas de dépassement de l'appétence | E14: =IF(D14="","",MATCH(D14,{"Non";"Partiellement";"Oui"},0)-1)
A15: 6. Traitement des risques | B15: 6.1 | C15: Chaque risque significatif fait l'objet d'un plan de traitement documentant le plan de rémédiation retenu, avec un responsable nommé, une échéance et un budget sécurisé. | E15: =IF(D15="","",MATCH(D15,{"Non";"Partiellement";"Oui"},0)-1)
B16: 6.2 | C16: Nous testons l'efficacité réelle des traitements mis en place, et pas seulement leur mise en œuvre, et les retards ou insuffisances font l'objet d'une escalade formelle. | E16: =IF(D16="","",MATCH(D16,{"Non";"Partiellement";"Oui"},0)-1)
A17: 7. Revue et révision | B17: 7.1 | C17: Nous évaluons l'efficacité de notre dispositif de gestion des risques selon un rythme planifié | E17: =IF(D17="","",MATCH(D17,{"Non";"Partiellement";"Oui"},0)-1)
B18: 7.2 | C18: Nous recueillons et intégrons les enseignements tirés des incidents et des interruptions d'activité et situations d'urgence passées afin d'améliorer en continu notre dispositif | E18: =IF(D18="","",MATCH(D18,{"Non";"Partiellement";"Oui"},0)-1)
A19: 8. Information et reporting | B19: 8.1 | C19: Nous disposons d'indicateurs de risque (KRI) reliés à nos risques et objectifs | E19: =IF(D19="","",MATCH(D19,{"Non";"Partiellement";"Oui"},0)-1)
B20: 8.2 | C20: L'information critique sur les risques remonte aux instances de décision dans des délais convenus | E20: =IF(D20="","",MATCH(D20,{"Non";"Partiellement";"Oui"},0)-1)
A21: 9. Continuité d'activité (PCA/PRA) | B21: 9.1 | C21: Nous disposons d'une analyse d'impact sur l'activité (BIA) couvrant nos processus critiques, avec des RTO/RPO validés par les métiers et intégrant les dépendances SI, fournisseurs, sites et compétences, revue périodiquement | E21: =IF(D21="","",MATCH(D21,{"Non";"Partiellement";"Oui"},0)-1)
B22: 9.2 | C22: Nous testons nos plans de continuité et de reprise selon un programme planifié couvrant plusieurs scénarios | E22: =IF(D22="","",MATCH(D22,{"Non";"Partiellement";"Oui"},0)-1)
A23: 10. Gestion de crise (PGC) | B23: 10.1 | C23: Nous disposons d'un dispositif de crise formalisé et gradué : composition et suppléance de la cellule, critères et niveaux d'activation, chaîne d'alerte et moyens de communication | E23: =IF(D23="","",MATCH(D23,{"Non";"Partiellement";"Oui"},0)-1)
B24: 10.2 | C24: Nous réalisons les activités du programme de gestion de crise — élaboration des plans de réponse, formations et exercices impliquant la direction générale — de manière planifiée, régulière et cohérente | E24: =IF(D24="","",MATCH(D24,{"Non";"Partiellement";"Oui"},0)-1)
A25: 11. Résilience organisationnelle | B25: 11.1 | C25: Nous disposons d'une cartographie à jour de nos dépendances critiques (fournisseurs, sites, systèmes, compétences rares), reliée à nos activités critiques et permettant d'identifier nos points de défaillance unique. | E25: =IF(D25="","",MATCH(D25,{"Non";"Partiellement";"Oui"},0)-1)
B26: 11.2 | C26: La résilience est un critère explicite et documenté de nos décisions structurantes (architecture, sourcing, implantation, projets), et notre capacité d'adaptation est mesurée après chaque perturbation réelle. | E26: =IF(D26="","",MATCH(D26,{"Non";"Partiellement";"Oui"},0)-1)
C28: Affirmations renseignées : | D28: =COUNTA(D5:D26)&" / 22" -> 0 / 22

Sheet 2. Résultats
B2: Résultats de l'évaluation
B3: Calcul automatique — aucune saisie requise sur cet onglet.
B5: Dimension | C5: Points /4 | D5: Taux | E5: Poids | F5: Niveau atteint | G5: Réponses
B6: 1. Stratégie | C6: =IF(COUNTA('1. Questionnaire'!D5:D6)<2,"",SUM('1. Questionnaire'!E5:E6)) | D6: =IF(C6="","",C6/4) | E6: ='0. Notice'!C41 -> 8 | F6: =IF(C6="","—",INDEX('0. Notice'!$D$31:$D$35,C6+1)) -> — | G6: =COUNTA('1. Questionnaire'!D5:D6)&" / 2" -> 0 / 2 | P6: =IF(C6="",0,D6*E6) -> 0 | Q6: =IF(C6="",0,E6) -> 0
B7: 2. Gouvernance | C7: =IF(COUNTA('1. Questionnaire'!D7:D8)<2,"",SUM('1. Questionnaire'!E7:E8)) | D7: =IF(C7="","",C7/4) | E7: ='0. Notice'!C42 -> 12 | F7: =IF(C7="","—",INDEX('0. Notice'!$D$31:$D$35,C7+1)) -> — | G7: =COUNTA('1. Questionnaire'!D7:D8)&" / 2" -> 0 / 2 | P7: =IF(C7="",0,D7*E7) -> 0 | Q7: =IF(C7="",0,E7) -> 0
B8: 3. Culture | C8: =IF(COUNTA('1. Questionnaire'!D9:D10)<2,"",SUM('1. Questionnaire'!E9:E10)) | D8: =IF(C8="","",C8/4) | E8: ='0. Notice'!C43 -> 8 | F8: =IF(C8="","—",INDEX('0. Notice'!$D$31:$D$35,C8+1)) -> — | G8: =COUNTA('1. Questionnaire'!D9:D10)&" / 2" -> 0 / 2 | P8: =IF(C8="",0,D8*E8) -> 0 | Q8: =IF(C8="",0,E8) -> 0
B9: 4. Identification des risques | C9: =IF(COUNTA('1. Questionnaire'!D11:D12)<2,"",SUM('1. Questionnaire'!E11:E12)) | D9: =IF(C9="","",C9/4) | E9: ='0. Notice'!C44 -> 10 | F9: =IF(C9="","—",INDEX('0. Notice'!$D$31:$D$35,C9+1)) -> — | G9: =COUNTA('1. Questionnaire'!D11:D12)&" / 2" -> 0 / 2 | P9: =IF(C9="",0,D9*E9) -> 0 | Q9: =IF(C9="",0,E9) -> 0
B10: 5. Analyse et évaluation des risques | C10: =IF(COUNTA('1. Questionnaire'!D13:D14)<2,"",SUM('1. Questionnaire'!E13:E14)) | D10: =IF(C10="","",C10/4) | E10: ='0. Notice'!C45 -> 10 | F10: =IF(C10="","—",INDEX('0. Notice'!$D$31:$D$35,C10+1)) -> — | G10: =COUNTA('1. Questionnaire'!D13:D14)&" / 2" -> 0 / 2 | P10: =IF(C10="",0,D10*E10) -> 0 | Q10: =IF(C10="",0,E10) -> 0
B11: 6. Traitement des risques | C11: =IF(COUNTA('1. Questionnaire'!D15:D16)<2,"",SUM('1. Questionnaire'!E15:E16)) | D11: =IF(C11="","",C11/4) | E11: ='0. Notice'!C46 -> 10 | F11: =IF(C11="","—",INDEX('0. Notice'!$D$31:$D$35,C11+1)) -> — | G11: =COUNTA('1. Questionnaire'!D15:D16)&" / 2" -> 0 / 2 | P11: =IF(C11="",0,D11*E11) -> 0 | Q11: =IF(C11="",0,E11) -> 0
B12: 7. Revue et révision | C12: =IF(COUNTA('1. Questionnaire'!D17:D18)<2,"",SUM('1. Questionnaire'!E17:E18)) | D12: =IF(C12="","",C12/4) | E12: ='0. Notice'!C47 -> 7 | F12: =IF(C12="","—",INDEX('0. Notice'!$D$31:$D$35,C12+1)) -> — | G12: =COUNTA('1. Questionnaire'!D17:D18)&" / 2" -> 0 / 2 | P12: =IF(C12="",0,D12*E12) -> 0 | Q12: =IF(C12="",0,E12) -> 0
B13: 8. Information et reporting | C13: =IF(COUNTA('1. Questionnaire'!D19:D20)<2,"",SUM('1. Questionnaire'!E19:E20)) | D13: =IF(C13="","",C13/4) | E13: ='0. Notice'!C48 -> 7 | F13: =IF(C13="","—",INDEX('0. Notice'!$D$31:$D$35,C13+1)) -> — | G13: =COUNTA('1. Questionnaire'!D19:D20)&" / 2" -> 0 / 2 | P13: =IF(C13="",0,D13*E13) -> 0 | Q13: =IF(C13="",0,E13) -> 0
B14: 9. Continuité d'activité (PCA/PRA) | C14: =IF(COUNTA('1. Questionnaire'!D21:D22)<2,"",SUM('1. Questionnaire'!E21:E22)) | D14: =IF(C14="","",C14/4) | E14: ='0. Notice'!C49 -> 12 | F14: =IF(C14="","—",INDEX('0. Notice'!$D$31:$D$35,C14+1)) -> — | G14: =COUNTA('1. Questionnaire'!D21:D22)&" / 2" -> 0 / 2 | P14: =IF(C14="",0,D14*E14) -> 0 | Q14: =IF(C14="",0,E14) -> 0
B15: 10. Gestion de crise (PGC) | C15: =IF(COUNTA('1. Questionnaire'!D23:D24)<2,"",SUM('1. Questionnaire'!E23:E24)) | D15: =IF(C15="","",C15/4) | E15: ='0. Notice'!C50 -> 10 | F15: =IF(C15="","—",INDEX('0. Notice'!$D$31:$D$35,C15+1)) -> — | G15: =COUNTA('1. Questionnaire'!D23:D24)&" / 2" -> 0 / 2 | P15: =IF(C15="",0,D15*E15) -> 0 | Q15: =IF(C15="",0,E15) -> 0
B16: 11. Résilience organisationnelle | C16: =IF(COUNTA('1. Questionnaire'!D25:D26)<2,"",SUM('1. Questionnaire'!E25:E26)) | D16: =IF(C16="","",C16/4) | E16: ='0. Notice'!C51 -> 6 | F16: =IF(C16="","—",INDEX('0. Notice'!$D$31:$D$35,C16+1)) -> — | G16: =COUNTA('1. Questionnaire'!D25:D26)&" / 2" -> 0 / 2 | P16: =IF(C16="",0,D16*E16) -> 0 | Q16: =IF(C16="",0,E16) -> 0
B17: SCORE GLOBAL PONDÉRÉ | D17: =IF(SUM(Q6:Q16)=0,"",SUM(P6:P16)/SUM(Q6:Q16)) | E17: =SUM(E6:E16) -> 100 | F17: =IF(D17="","—",INDEX('0. Notice'!$D$31:$D$35,MATCH(D17,{0;0.125;0.375;0.625;0.875},1))) -> —
B20: Lecture du score global
B21: Taux global | C21: Niveau
B22: 0 – 12 % | C22: Émergent
B23: 13 – 37 % | C23: En progression
B24: 38 – 62 % | C24: Établi
B25: 63 – 87 % | C25: Avancé
B26: 88 – 100 % | C26: Aspirationnel

Sheet 3. Recommandations
A1: Recommandations personnalisées
A2: Généré automatiquement à partir du niveau atteint sur chaque dimension. Traitez en priorité les dimensions dont le taux apparaît en rouge ou en orange, en tenant compte de leur poids.
A4: Dimension | B4: Taux | C4: Niveau | D4: Diagnostic | E4: Actions court terme (0–6 mois) | F4: Actions moyen terme (6–18 mois)
A5: ='2. Résultats'!B6 -> 1. Stratégie | B5: ='2. Résultats'!D6 | C5: ='2. Résultats'!F6 -> — | D5: =IFERROR(INDEX('4. Référentiel recos'!$D$4:$D$58,MATCH('2. Résultats'!$B$6&"|"&'2. Résultats'!$F$6,'4. Référentiel recos'!$A$4:$A$58,0)),"Complétez les 2 affirmations de cette dimension.") -> Complétez les 2 affirmations de cette dimension. | E5: =IFERROR(INDEX('4. Référentiel recos'!$E$4:$E$58,MATCH('2. Résultats'!$B$6&"|"&'2. Résultats'!$F$6,'4. Référentiel recos'!$A$4:$A$58,0)),"Complétez les 2 affirmations de cette dimension.") -> Complétez les 2 affirmations de cette dimension. | F5: =IFERROR(INDEX('4. Référentiel recos'!$F$4:$F$58,MATCH('2. Résultats'!$B$6&"|"&'2. Résultats'!$F$6,'4. Référentiel recos'!$A$4:$A$58,0)),"Complétez les 2 affirmations de cette dimension.") -> Complétez les 2 affirmations de cette dimension.
A6: ='2. Résultats'!B7 -> 2. Gouvernance | B6: ='2. Résultats'!D7 | C6: ='2. Résultats'!F7 -> — | D6: =IFERROR(INDEX('4. Référentiel recos'!$D$4:$D$58,MATCH('2. Résultats'!$B$7&"|"&'2. Résultats'!$F$7,'4. Référentiel recos'!$A$4:$A$58,0)),"Complétez les 2 affirmations de cette dimension.") -> Complétez les 2 affirmations de cette dimension. | E6: =IFERROR(INDEX('4. Référentiel recos'!$E$4:$E$58,MATCH('2. Résultats'!$B$7&"|"&'2. Résultats'!$F$7,'4. Référentiel recos'!$A$4:$A$58,0)),"Complétez les 2 affirmations de cette dimension.") -> Complétez les 2 affirmations de cette dimension. | F6: =IFERROR(INDEX('4. Référentiel recos'!$F$4:$F$58,MATCH('2. Résultats'!$B$7&"|"&'2. Résultats'!$F$7,'4. Référentiel recos'!$A$4:$A$58,0)),"Complétez les 2 affirmations de cette dimension.") -> Complétez les 2 affirmations de cette dimension.
A7: ='2. Résultats'!B8 -> 3. Culture | B7: ='2. Résultats'!D8 | C7: ='2. Résultats'!F8 -> — | D7: =IFERROR(INDEX('4. Référentiel recos'!$D$4:$D$58,MATCH('2. Résultats'!$B$8&"|"&'2. Résultats'!$F$8,'4. Référentiel recos'!$A$4:$A$58,0)),"Complétez les 2 affirmations de cette dimension.") -> Complétez les 2 affirmations de cette dimension. | E7: =IFERROR(INDEX('4. Référentiel recos'!$E$4:$E$58,MATCH('2. Résultats'!$B$8&"|"&'2. Résultats'!$F$8,'4. Référentiel recos'!$A$4:$A$58,0)),"Complétez les 2 affirmations de cette dimension.") -> Complétez les 2 affirmations de cette dimension. | F7: =IFERROR(INDEX('4. Référentiel recos'!$F$4:$F$58,MATCH('2. Résultats'!$B$8&"|"&'2. Résultats'!$F$8,'4. Référentiel recos'!$A$4:$A$58,0)),"Complétez les 2 affirmations de cette dimension.") -> Complétez les 2 affirmations de cette dimension.
A8: ='2. Résultats'!B9 -> 4. Identification des risques | B8: ='2. Résultats'!D9 | C8: ='2. Résultats'!F9 -> — | D8: =IFERROR(INDEX('4. Référentiel recos'!$D$4:$D$58,MATCH('2. Résultats'!$B$9&"|"&'2. Résultats'!$F$9,'4. Référentiel recos'!$A$4:$A$58,0)),"Complétez les 2 affirmations de cette dimension.") -> Complétez les 2 affirmations de cette dimension. | E8: =IFERROR(INDEX('4. Référentiel recos'!$E$4:$E$58,MATCH('2. Résultats'!$B$9&"|"&'2. Résultats'!$F$9,'4. Référentiel recos'!$A$4:$A$58,0)),"Complétez les 2 affirmations de cette dimension.") -> Complétez les 2 affirmations de cette dimension. | F8: =IFERROR(INDEX('4. Référentiel recos'!$F$4:$F$58,MATCH('2. Résultats'!$B$9&"|"&'2. Résultats'!$F$9,'4. Référentiel recos'!$A$4:$A$58,0)),"Complétez les 2 affirmations de cette dimension.") -> Complétez les 2 affirmations de cette dimension.
A9: ='2. Résultats'!B10 -> 5. Analyse et évaluation des risques | B9: ='2. Résultats'!D10 | C9: ='2. Résultats'!F10 -> — | D9: =IFERROR(INDEX('4. Référentiel recos'!$D$4:$D$58,MATCH('2. Résultats'!$B$10&"|"&'2. Résultats'!$F$10,'4. Référentiel recos'!$A$4:$A$58,0)),"Complétez les 2 affirmations de cette dimension.") -> Complétez les 2 affirmations de cette dimension. | E9: =IFERROR(INDEX('4. Référentiel recos'!$E$4:$E$58,MATCH('2. Résultats'!$B$10&"|"&'2. Résultats'!$F$10,'4. Référentiel recos'!$A$4:$A$58,0)),"Complétez les 2 affirmations de cette dimension.") -> Complétez les 2 affirmations de cette dimension. | F9: =IFERROR(INDEX('4. Référentiel recos'!$F$4:$F$58,MATCH('2. Résultats'!$B$10&"|"&'2. Résultats'!$F$10,'4. Référentiel recos'!$A$4:$A$58,0)),"Complétez les 2 affirmations de cette dimension.") -> Complétez les 2 affirmations de cette dimension.
A10: ='2. Résultats'!B11 -> 6. Traitement des risques | B10: ='2. Résultats'!D11 | C10: ='2. Résultats'!F11 -> — | D10: =IFERROR(INDEX('4. Référentiel recos'!$D$4:$D$58,MATCH('2. Résultats'!$B$11&"|"&'2. Résultats'!$F$11,'4. Référentiel recos'!$A$4:$A$58,0)),"Complétez les 2 affirmations de cette dimension.") -> Complétez les 2 affirmations de cette dimension. | E10: =IFERROR(INDEX('4. Référentiel recos'!$E$4:$E$58,MATCH('2. Résultats'!$B$11&"|"&'2. Résultats'!$F$11,'4. Référentiel recos'!$A$4:$A$58,0)),"Complétez les 2 affirmations de cette dimension.") -> Complétez les 2 affirmations de cette dimension. | F10: =IFERROR(INDEX('4. Référentiel recos'!$F$4:$F$58,MATCH('2. Résultats'!$B$11&"|"&'2. Résultats'!$F$11,'4. Référentiel recos'!$A$4:$A$58,0)),"Complétez les 2 affirmations de cette dimension.") -> Complétez les 2 affirmations de cette dimension.
A11: ='2. Résultats'!B12 -> 7. Revue et révision | B11: ='2. Résultats'!D12 | C11: ='2. Résultats'!F12 -> — | D11: =IFERROR(INDEX('4. Référentiel recos'!$D$4:$D$58,MATCH('2. Résultats'!$B$12&"|"&'2. Résultats'!$F$12,'4. Référentiel recos'!$A$4:$A$58,0)),"Complétez les 2 affirmations de cette dimension.") -> Complétez les 2 affirmations de cette dimension. | E11: =IFERROR(INDEX('4. Référentiel recos'!$E$4:$E$58,MATCH('2. Résultats'!$B$12&"|"&'2. Résultats'!$F$12,'4. Référentiel recos'!$A$4:$A$58,0)),"Complétez les 2 affirmations de cette dimension.") -> Complétez les 2 affirmations de cette dimension. | F11: =IFERROR(INDEX('4. Référentiel recos'!$F$4:$F$58,MATCH('2. Résultats'!$B$12&"|"&'2. Résultats'!$F$12,'4. Référentiel recos'!$A$4:$A$58,0)),"Complétez les 2 affirmations de cette dimension.") -> Complétez les 2 affirmations de cette dimension.
A12: ='2. Résultats'!B13 -> 8. Information et reporting | B12: ='2. Résultats'!D13 | C12: ='2. Résultats'!F13 -> — | D12: =IFERROR(INDEX('4. Référentiel recos'!$D$4:$D$58,MATCH('2. Résultats'!$B$13&"|"&'2. Résultats'!$F$13,'4. Référentiel recos'!$A$4:$A$58,0)),"Complétez les 2 affirmations de cette dimension.") -> Complétez les 2 affirmations de cette dimension. | E12: =IFERROR(INDEX('4. Référentiel recos'!$E$4:$E$58,MATCH('2. Résultats'!$B$13&"|"&'2. Résultats'!$F$13,'4. Référentiel recos'!$A$4:$A$58,0)),"Complétez les 2 affirmations de cette dimension.") -> Complétez les 2 affirmations de cette dimension. | F12: =IFERROR(INDEX('4. Référentiel recos'!$F$4:$F$58,MATCH('2. Résultats'!$B$13&"|"&'2. Résultats'!$F$13,'4. Référentiel recos'!$A$4:$A$58,0)),"Complétez les 2 affirmations de cette dimension.") -> Complétez les 2 affirmations de cette dimension.
A13: ='2. Résultats'!B14 -> 9. Continuité d'activité (PCA/PRA) | B13: ='2. Résultats'!D14 | C13: ='2. Résultats'!F14 -> — | D13: =IFERROR(INDEX('4. Référentiel recos'!$D$4:$D$58,MATCH('2. Résultats'!$B$14&"|"&'2. Résultats'!$F$14,'4. Référentiel recos'!$A$4:$A$58,0)),"Complétez les 2 affirmations de cette dimension.") -> Complétez les 2 affirmations de cette dimension. | E13: =IFERROR(INDEX('4. Référentiel recos'!$E$4:$E$58,MATCH('2. Résultats'!$B$14&"|"&'2. Résultats'!$F$14,'4. Référentiel recos'!$A$4:$A$58,0)),"Complétez les 2 affirmations de cette dimension.") -> Complétez les 2 affirmations de cette dimension. | F13: =IFERROR(INDEX('4. Référentiel recos'!$F$4:$F$58,MATCH('2. Résultats'!$B$14&"|"&'2. Résultats'!$F$14,'4. Référentiel recos'!$A$4:$A$58,0)),"Complétez les 2 affirmations de cette dimension.") -> Complétez les 2 affirmations de cette dimension.
A14: ='2. Résultats'!B15 -> 10. Gestion de crise (PGC) | B14: ='2. Résultats'!D15 | C14: ='2. Résultats'!F15 -> — | D14: =IFERROR(INDEX('4. Référentiel recos'!$D$4:$D$58,MATCH('2. Résultats'!$B$15&"|"&'2. Résultats'!$F$15,'4. Référentiel recos'!$A$4:$A$58,0)),"Complétez les 2 affirmations de cette dimension.") -> Complétez les 2 affirmations de cette dimension. | E14: =IFERROR(INDEX('4. Référentiel recos'!$E$4:$E$58,MATCH('2. Résultats'!$B$15&"|"&'2. Résultats'!$F$15,'4. Référentiel recos'!$A$4:$A$58,0)),"Complétez les 2 affirmations de cette dimension.") -> Complétez les 2 affirmations de cette dimension. | F14: =IFERROR(INDEX('4. Référentiel recos'!$F$4:$F$58,MATCH('2. Résultats'!$B$15&"|"&'2. Résultats'!$F$15,'4. Référentiel recos'!$A$4:$A$58,0)),"Complétez les 2 affirmations de cette dimension.") -> Complétez les 2 affirmations de cette dimension.
A15: ='2. Résultats'!B16 -> 11. Résilience organisationnelle | B15: ='2. Résultats'!D16 | C15: ='2. Résultats'!F16 -> — | D15: =IFERROR(INDEX('4. Référentiel recos'!$D$4:$D$58,MATCH('2. Résultats'!$B$16&"|"&'2. Résultats'!$F$16,'4. Référentiel recos'!$A$4:$A$58,0)),"Complétez les 2 affirmations de cette dimension.") -> Complétez les 2 affirmations de cette dimension. | E15: =IFERROR(INDEX('4. Référentiel recos'!$E$4:$E$58,MATCH('2. Résultats'!$B$16&"|"&'2. Résultats'!$F$16,'4. Référentiel recos'!$A$4:$A$58,0)),"Complétez les 2 affirmations de cette dimension.") -> Complétez les 2 affirmations de cette dimension. | F15: =IFERROR(INDEX('4. Référentiel recos'!$F$4:$F$58,MATCH('2. Résultats'!$B$16&"|"&'2. Résultats'!$F$16,'4. Référentiel recos'!$A$4:$A$58,0)),"Complétez les 2 affirmations de cette dimension.") -> Complétez les 2 affirmations de cette dimension.

Sheet 4. Référentiel recos
A1: Référentiel des recommandations (11 dimensions × 5 niveaux) — onglet technique, ne pas modifier
A3: Clé | B3: Dimension | C3: Niveau | D3: Diagnostic | E3: Actions court terme (0–6 mois) | F3: Actions moyen terme (6–18 mois)
A4: 1. Stratégie|Émergent | B4: 1. Stratégie | C4: Émergent | D4: La stratégie est pilotée sans lecture prospective des risques : les décisions subissent les événements au lieu de les anticiper. | E4: Introduire un point « principaux risques de mise en œuvre » dans le prochain cycle de planification et recenser les 10 risques majeurs pouvant compromettre les objectifs de l'année. | F4: Formaliser une première déclaration d'appétit au risque validée par la direction générale et reliée aux objectifs stratégiques.
A5: 1. Stratégie|En progression | B5: 1. Stratégie | C5: En progression | D5: Le lien entre stratégie et risque existe mais reste ponctuel et déconnecté de l'appétit au risque. | E5: Structurer l'analyse des risques stratégiques selon un format unique appliqué à toutes les directions, et relier chaque objectif majeur à ses risques d'atteinte. | F5: Publier une déclaration d'appétit au risque intégrant les arbitrages et l'utiliser explicitement lors des arbitrages budgétaires.
A6: 1. Stratégie|Établi | B6: 1. Stratégie | C6: Établi | D6: La démarche est en place et cohérente ; le potentiel de progression porte sur la prospective et la granularité de l'appétit au risque. | E6: Mettre en place une revue semestrielle de l'appétit au risque par la gouvernance, à la lumière des événements survenus. | F6: Déployer une veille prospective et des exercices de scénarios impliquant des parties prenantes externes (régulateur, fournisseurs clés, pairs).
A7: 1. Stratégie|Avancé | B7: 1. Stratégie | C7: Avancé | D7: Le dispositif est mature ; l'enjeu devient la finesse et la réactivité des ajustements. | E7: Décliner l'appétit au risque en tolérances chiffrées par domaine et les intégrer aux tableaux de bord de direction. | F7: Réduire le délai entre le signal de risque et l'ajustement de trajectoire, par un suivi rapproché des indicateurs stratégiques.
A8: 1. Stratégie|Aspirationnel | B8: 1. Stratégie | C8: Aspirationnel | D8: Niveau de référence. L'enjeu est le maintien dans la durée. | E8: Documenter la démarche pour la pérenniser au-delà des personnes en place. | F8: Faire challenger le modèle par des revues externes indépendantes pour éviter l'auto-satisfaction.
A9: 2. Gouvernance|Émergent | B9: 2. Gouvernance | C9: Émergent | D9: L'absence de structure claire empêche toute responsabilisation : les risques n'ont pas de propriétaire et ne sont pas arbitrés. | E9: Désigner un responsable de la gestion des risques et un sponsor au niveau de la direction générale, et recenser les instances existantes et leur rôle réel. | F9: Créer un comité des risques doté d'un mandat écrit, d'une fréquence de réunion et d'un ordre du jour type.
A10: 2. Gouvernance|En progression | B10: 2. Gouvernance | C10: En progression | D10: Une gouvernance existe mais reste cloisonnée : l'information circule mal entre instances et la responsabilité est partielle. | E10: Formaliser un mandat écrit pour chaque instance, supprimer les zones de recouvrement et instaurer un reporting périodique standard au comité de direction. | F10: Déployer une matrice RACI des risques par direction et clarifier l'articulation entre métiers, fonction risque et audit.
A11: 2. Gouvernance|Établi | B11: 2. Gouvernance | C11: Établi | D11: La gouvernance est structurée et fonctionne ; les marges portent sur la profondeur des arbitrages et la coordination des lignes de défense. | E11: Faire approuver formellement les tolérances au risque pour les risques majeurs par l'instance transverse. | F11: Construire un plan d'assurance coordonné entre fonction risque, conformité et audit pour éliminer angles morts et doublons.
A12: 2. Gouvernance|Avancé | B12: 2. Gouvernance | C12: Avancé | D12: Gouvernance solide. L'enjeu est la vérification indépendante de son efficacité réelle. | E12: Soumettre le dispositif à une évaluation indépendante portant sur son efficacité, et pas seulement sur sa conformité. | F12: Développer la capacité de décision rapide hors calendrier pour les risques à cinétique courte.
A13: 2. Gouvernance|Aspirationnel | B13: 2. Gouvernance | C13: Aspirationnel | D13: Niveau de référence. Le risque principal devient la complaisance. | E13: Maintenir la cadence des évaluations indépendantes et faire challenger la gouvernance par des regards externes. | F13: Tester le dispositif sur des scénarios inédits plutôt que sur ceux déjà maîtrisés.
A14: 3. Culture|Émergent | B14: 3. Culture | C14: Émergent | D14: La gestion des risques est perçue comme une contrainte administrative ; les alertes ne remontent pas. | E14: Faire porter un message explicite par la direction générale sur l'attendu en matière de risque, et créer un canal de remontée d'alerte identifié et communiqué. | F14: Déployer une sensibilisation de base à l'ensemble de l'encadrement, appuyée sur des cas concrets issus de l'entreprise.
... A58: 11. Résilience organisationnelle|Aspirationnel | B58: 11. Résilience organisationnelle | C58: Aspirationnel | D58: Niveau de référence. | E58: Vérifier que la résilience conçue tient face à des perturbations non anticipées par les modèles. | F58: Préserver les marges de manœuvre (redondances, stocks, polyvalence) que l'optimisation économique tend à éroder.
