Workbook

Sheet 0. Notice
B2: Questionnaire d'évaluation de maturité — Gestion des risques d'entreprise (ERM)
B3: Référentiel adapté de : OECD (2021), Enterprise Risk Management Maturity Model — étendu aux dimensions Continuité, Gestion de crise et Résilience.
B5: Fiche d'identité de l'entité évaluée
B6: Nom de l'entité
B7: Secteur d'activité
B8: Effectif
B9: Périmètre évalué
B10: Personne référente
B11: Fonction
B12: Date de l'évaluation
B15: Mode d'emploi
B16: 1. Rendez-vous sur l'onglet « 1. Questionnaire ». Il comporte 33 questions réparties sur 11 dimensions.
... B25: Échelle de maturité
B26: Lettre | C26: Points | D26: Niveau de maturité
B27: A | C27: 1 | D27: Émergent
B28: B | C28: 2 | D28: En progression
B29: C | C29: 3 | D29: Établi
B30: D | C30: 4 | D30: Avancé
B31: E | C31: 5 | D31: Aspirationnel
B34: Pondération des dimensions
B35: Les poids ci-dessous sont modifiables. Le score global est la moyenne pondérée des scores par dimension.
B36: Dimension | C36: Poids
B37: 1. Stratégie | C37: 8
B38: 2. Gouvernance | C38: 12
B39: 3. Culture | C39: 8
B40: 4. Identification des risques | C40: 10
B41: 5. Analyse et évaluation des risques | C41: 10
B42: 6. Traitement des risques | C42: 10
B43: 7. Revue et révision | C43: 7
B44: 8. Information et reporting | C44: 7
B45: 9. Continuité d'activité (PCA/PRA) | C45: 12
B46: 10. Gestion de crise (PGC) | C46: 10
B47: 11. Résilience organisationnelle | C47: 6
B48: Total | C48: =SUM(C37:C47) -> 100

Sheet 1. Questionnaire
A1: Questionnaire — sélectionnez une lettre (A à E) dans la colonne « Réponse »
A3: Dimension | B3: N° | C3: Question | D3: A — Émergent | E3: B — En progression | F3: C — Établi | G3: D — Avancé | H3: E — Aspirationnel | I3: Réponse | J3: Points | K3: Commentaire / preuve
A4: 1. Stratégie | B4: 1.1 | C4: La stratégie et les objectifs de l'entreprise intègrent-ils une analyse prospective des risques ? | D4: La stratégie est ajustée a posteriori, principalement en fonction des risques déjà survenus. | E4: Une analyse partielle des risques de mise en œuvre est réalisée, mais pas de façon systématique. | F4: Les changements majeurs de l'environnement interne/externe sont pris en compte, avec des ajustements conformes à l'appétit au risque général. | G4: La stratégie s'appuie sur une veille prospective et des scénarios impliquant un large éventail de parties prenantes internes et externes. | H4: La planification stratégique est continue, assistée par des outils analytiques avancés, avec ajustements en temps réel. | J4: =IF(I4="","",MATCH(I4,{"A";"B";"C";"D";"E"},0))
B5: 1.2 | C5: L'appétit au risque de l'entreprise est-il formalisé et relié à la stratégie ? | D5: La direction n'a qu'une compréhension limitée de la notion d'appétit au risque. | E5: Une compréhension de base existe mais n'est pas reliée à la stratégie. | F5: Une déclaration d'appétit au risque, intégrant les arbitrages, existe et est communiquée. | G5: Des déclarations d'appétit au risque existent par domaine clé et sont revues périodiquement par la gouvernance. | H5: L'appétit au risque est intégré à tous les objectifs métier et surveillé en continu, avec propositions d'ajustement automatisées. | J5: =IF(I5="","",MATCH(I5,{"A";"B";"C";"D";"E"},0))
B6: 1.3 | C6: Les risques sont-ils pris en compte dans l'allocation des ressources et les arbitrages d'investissement ? | D6: L'allocation des ressources ne tient pas compte formellement des risques. | E6: Le risque est évoqué pour les investissements les plus importants, de façon non structurée. | F6: L'information sur les risques alimente l'allocation des ressources, surtout dans les domaines les plus exposés. | G6: Les arbitrages d'investissement intègrent systématiquement le profil de risque et la tolérance définie. | H6: L'allocation est optimisée en continu selon un modèle risque/rendement alimenté par des données en temps réel. | J6: =IF(I6="","",MATCH(I6,{"A";"B";"C";"D";"E"},0))
A7: 2. Gouvernance | B7: 2.1 | C7: Comment la gouvernance de la gestion des risques est-elle structurée ? | D7: La structure de gouvernance est floue et peu coordonnée entre les instances. | E7: Une structure existe avec des échanges ponctuels et un reporting périodique au comité de direction. | F7: Une structure transverse assure la revue périodique des risques et fixe l'appétit au risque général. | G7: Une structure transverse revoit régulièrement risques et performance, et approuve appétit et tolérance pour les risques majeurs. | H7: Une instance transverse prend des décisions proactives, y compris en temps réel, sur le risque et la performance. | J7: =IF(I7="","",MATCH(I7,{"A";"B";"C";"D";"E"},0))
B8: 2.2 | C8: Les rôles, responsabilités et niveaux d'autorité sont-ils définis et appliqués ? | D8: Ils sont peu documentés et appliqués de façon incohérente ; la responsabilité est peu claire. | E8: Ils sont définis dans certains domaines, avec un focus sur les risques majeurs. | F8: Une structure opérationnelle définit autorité et responsabilités, appliquée de façon cohérente dans la plupart des unités. | G8: Les rôles et niveaux d'autorité sont cartographiés dans les plans opérationnels et les objectifs individuels. | H8: Les rôles, délégations et structures de gouvernance sont revus périodiquement, y compris par des évaluations indépendantes. | J8: =IF(I8="","",MATCH(I8,{"A";"B";"C";"D";"E"},0))
B9: 2.3 | C9: Le dispositif de lignes de défense (métiers, risques/conformité, audit) est-il en place ? | D9: Il n'existe pas de séparation claire entre les fonctions opérationnelles et le contrôle des risques. | E9: Une fonction risque ou conformité existe, mais son articulation avec l'audit et les métiers reste ambiguë. | F9: Les trois lignes de défense sont formalisées, avec des périmètres et des rattachements définis. | G9: Les lignes de défense sont coordonnées, avec des plans d'assurance partagés et une couverture des risques revue conjointement. | H9: Le modèle d'assurance est intégré, piloté par les données, et son efficacité fait l'objet d'évaluations indépendantes régulières. | J9: =IF(I9="","",MATCH(I9,{"A";"B";"C";"D";"E"},0))
A10: 3. Culture | B10: 3.1 | C10: Comment la direction promeut-elle la gestion des risques ? | D10: La direction a une appréciation générale des risques mais ne promeut pas la démarche de façon proactive. | E10: La direction promeut la démarche, surtout pour les projets à fort enjeu réputationnel. | F10: L'importance d'une gestion des risques transverse est soulignée par la direction et reflétée dans la formation et le management. | G10: Une culture forte du risque est encouragée, soutenue par une formation continue et valorisée dans l'évaluation de la performance. | H10: La gestion des risques est intégrée aux valeurs de l'entreprise et aux comportements quotidiens, dans une culture d'innovation. | J10: =IF(I10="","",MATCH(I10,{"A";"B";"C";"D";"E"},0))
B11: 3.2 | C11: Quel est le niveau d'expertise et de formation en gestion des risques ? | D11: La pratique dépend de l'expertise individuelle des managers ; la formation se fait surtout sur le terrain. | E11: Une expertise interne existe ; la formation est réactive et ciblée sur les projets identifiés comme à risque. | F11: La décision éclairée par le risque est encouragée et soutenue par des experts disponibles sur demande. | G11: Les attentes sont communiquées à tous les niveaux ; la culture du risque est mesurée et comparée à d'autres organisations. | H11: Les comportements et décisions sont suivis en continu pour vérifier leur alignement avec les valeurs et l'appétit au risque. | J11: =IF(I11="","",MATCH(I11,{"A";"B";"C";"D";"E"},0))
B12: 3.3 | C12: Les collaborateurs peuvent-ils remonter un risque ou une alerte sans crainte ? | D12: Il n'existe pas de canal identifié ; remonter un problème est perçu comme risqué pour celui qui le signale. | E12: Des canaux existent pour certains sujets (fraude, sécurité) mais sont peu connus ou peu utilisés. | F12: Un dispositif de remontée est en place, communiqué, et les alertes sont traitées selon un processus défini. | G12: La remontée d'alerte est encouragée et valorisée ; les suites données sont communiquées en retour aux émetteurs. | H12: La culture de transparence est mesurée activement ; les signaux faibles remontent spontanément et alimentent le dispositif de risque. | J12: =IF(I12="","",MATCH(I12,{"A";"B";"C";"D";"E"},0))
A13: 4. Identification des risques | B13: 4.1 | C13: Comment les risques sont-ils identifiés au sein de l'entreprise ? | D13: L'identification est laissée aux managers individuels, sans méthode commune. | E13: Des exigences de reporting standardisées existent, mais le processus et la qualité varient selon les unités. | F13: Les principaux risques sont identifiés à intervalles réguliers selon un processus standardisé. | G13: Les risques sont identifiés et validés de façon cohérente à tous les niveaux, en intégrant les retours d'expérience. | H13: Les risques nouveaux ou émergents sont identifiés en continu à partir de sources internes et externes variées. | J13: =IF(I13="","",MATCH(I13,{"A";"B";"C";"D";"E"},0))
B14: 4.2 | C14: Existe-t-il une vision consolidée (portefeuille) des risques au niveau de l'entreprise ? | D14: Non, les risques ne sont pas centralisés, rendant impossible une vision cohérente. | E14: Les risques majeurs des unités sont remontés au niveau entreprise après validation par la direction. | F14: Une vision de portefeuille validée par la gouvernance existe, avec un profil de risque par niveau. | G14: L'identification intègre les interrelations entre risques et est diffusée dans les plans à tous les niveaux. | H14: Les risques et leurs interrelations font l'objet de revues par les pairs et sont intégrés aux objectifs globaux. | J14: =IF(I14="","",MATCH(I14,{"A";"B";"C";"D";"E"},0))
B15: 4.3 | C15: Une veille sur les risques émergents (horizon scanning) est-elle organisée ? | D15: Aucune veille organisée ; les nouveaux risques sont découverts lorsqu'ils se matérialisent. | E15: Une veille informelle existe, portée par quelques personnes, sans restitution structurée. | F15: Une veille est organisée périodiquement et ses conclusions sont présentées à la gouvernance. | G15: La veille couvre plusieurs horizons et alimente formellement la révision de la cartographie des risques. | H15: La veille est continue, outillée, et déclenche automatiquement des réévaluations de risques. | J15: =IF(I15="","",MATCH(I15,{"A";"B";"C";"D";"E"},0))
A16: 5. Analyse et évaluation des risques | B16: 5.1 | C16: Quelles méthodes d'analyse des risques sont utilisées ? | D16: Les risques ne sont pas analysés formellement, ou de façon incohérente selon le jugement individuel. | E16: L'analyse est standardisée mais basique, reposant sur des jugements subjectifs variables selon les unités. | F16: Des techniques quantitatives standardisées complètent l'analyse qualitative ; des scénarios sont utilisés sur les zones à risque. | G16: Les approches quantitatives sont systématiques ; scénarios et simulations sont réguliers, avec des seuils déclencheurs de réévaluation. | H16: L'analyse s'appuie sur un système intégré combinant données internes/externes en temps réel et modélisation cause-effet. | J16: =IF(I16="","",MATCH(I16,{"A";"B";"C";"D";"E"},0))
B17: 5.2 | C17: Comment les risques sont-ils priorisés ? | D17: La priorisation se limite aux projets à fort enjeu réputationnel ; le reste suit une logique de routine. | E17: Une mesure large de l'ampleur des risques est dérivée de jugements qualitatifs de probabilité et d'impact. | F17: Un portefeuille priorisé de risques existe, articulé autour des objectifs métier et des opportunités associées. | G17: Le portefeuille priorisé est évalué dans le contexte global des objectifs, en croisant vues descendante et ascendante. | H17: Le portefeuille est mis à jour en continu et intègre les risques portés par l'écosystème externe. | J17: =IF(I17="","",MATCH(I17,{"A";"B";"C";"D";"E"},0))
B18: 5.3 | C18: Le risque résiduel (après contrôles) est-il distingué du risque brut et mesuré ? | D18: La notion de risque résiduel n'est pas utilisée. | E18: La distinction est connue mais appliquée de façon irrégulière selon les unités. | F18: Risque brut et résiduel sont évalués de façon standardisée pour les risques significatifs. | G18: Le risque résiduel est systématiquement rapporté à la tolérance définie, avec escalade en cas de dépassement. | H18: Le risque résiduel est recalculé dynamiquement en fonction de l'efficacité mesurée des contrôles. | J18: =IF(I18="","",MATCH(I18,{"A";"B";"C";"D";"E"},0))
A19: 6. Traitement des risques | B19: 6.1 | C19: Comment les plans de traitement sont-ils élaborés ? | D19: Il n'existe pas de plan formalisé, hormis quelques mesures de contingence ponctuelles. | E19: Des plans sont développés par unité, dans un format standardisé mais avec une approche souvent subjective. | F19: Les plans sont développés de façon standardisée et éclairée par les données, avec une coordination entre unités. | G19: L'ensemble des options est testé de façon transverse, y compris pour les risques interreliés ; les résultats sont mesurés. | H19: Les options de traitement sont générées par un système intégré calculant coûts/bénéfices sur un large jeu de paramètres. | J19: =IF(I19="","",MATCH(I19,{"A";"B";"C";"D";"E"},0))
B20: 6.2 | C20: Comment le suivi de l'efficacité des traitements est-il assuré ? | D20: Le suivi se limite aux activités d'audit ou de conformité ; peu de remontée hors projets phares. | E20: Les traitements sont mis en œuvre par unité et reportés périodiquement, avec une validation limitée. | F20: La gouvernance examine et challenge régulièrement les propositions de traitement au niveau entreprise. | G20: La validation des plans, y compris leurs interrelations, est transverse ; leur efficacité est testée périodiquement. | H20: Les traitements sont surveillés en continu, avec des recommandations d'ajustement formulées en temps réel. | J20: =IF(I20="","",MATCH(I20,{"A";"B";"C";"D";"E"},0))
B21: 6.3 | C21: Les plans d'action sont-ils dotés d'un responsable, d'une échéance et de moyens ? | D21: Les actions décidées ne sont ni nommément attribuées ni datées. | E21: Un responsable est désigné, mais les échéances glissent sans conséquence et les moyens ne sont pas sécurisés. | F21: Chaque action a un responsable, une échéance et un budget identifiés, suivis dans un outil ou un tableau centralisé. | G21: Le suivi des actions est intégré au pilotage de la performance ; les retards font l'objet d'une escalade formelle. | H21: L'avancement des actions est suivi en continu, avec alertes automatiques et réallocation dynamique des moyens. | J21: =IF(I21="","",MATCH(I21,{"A";"B";"C";"D";"E"},0))
A22: 7. Revue et révision | B22: 7.1 | C22: À quelle fréquence et selon quelle méthode l'efficacité du dispositif est-elle évaluée ? | D22: Les revues sont réalisées de façon réactive, après un incident majeur ou un impact réputationnel. | E22: L'efficacité est évaluée de façon générale une fois par an, ainsi qu'après un risque majeur survenu. | F22: Des revues régulières sont menées sur les zones à risque élevé, avec des plans d'action suivis par la direction. | G22: Les résultats sont intégrés au reporting de performance régulier et comparés à d'autres organisations. | H22: L'efficacité est évaluée en continu et fait l'objet de revues indépendantes contre les meilleures pratiques. | J22: =IF(I22="","",MATCH(I22,{"A";"B";"C";"D";"E"},0))
B23: 7.2 | C23: Les recommandations issues des revues donnent-elles lieu à des actions suivies ? | D23: Les changements se limitent à l'enjeu ponctuel ayant déclenché la revue. | E23: Des recommandations sont transmises aux responsables concernés, sans suivi systématique. | F23: Des plans d'action sont mis en place et leur avancement est suivi par la direction. | G23: Le suivi est systématique, intégré au reporting régulier, avec escalade des recommandations non soldées. | H23: Le suivi est continu et l'efficacité réelle des recommandations mises en œuvre est mesurée. | J23: =IF(I23="","",MATCH(I23,{"A";"B";"C";"D";"E"},0))
B24: 7.3 | C24: Le dispositif est-il ajusté après un incident réel (boucle d'apprentissage) ? | D24: Les incidents ne donnent pas lieu à une révision du dispositif. | E24: Un retour d'expérience est fait pour les incidents majeurs, mais les enseignements restent locaux. | F24: Les RETEX alimentent la révision de la cartographie et des plans de traitement concernés. | G24: Les enseignements sont diffusés à l'ensemble de l'organisation et intégrés aux processus, pas seulement au domaine touché. | H24: L'apprentissage est systématisé : chaque événement, y compris les quasi-incidents, alimente l'ajustement du dispositif. | J24: =IF(I24="","",MATCH(I24,{"A";"B";"C";"D";"E"},0))
A25: 8. Information et reporting | B25: 8.1 | C25: Comment l'information sur les risques est-elle collectée et partagée ? | D25: L'extraction est largement manuelle, avec une qualité très variable selon les unités. | E25: Des modèles de reporting et des canaux sont définis, mais appliqués de façon inégale. | F25: Les systèmes existants sont utilisés pour collecter l'information ; standards et propriété des données sont définis. | G25: Des données fiables et actualisées sont intégrées au reporting et accessibles à la demande via un référentiel central. | H25: Des outils d'analyse avancés produisent une information exploitable, de plus en plus en temps réel et accessible largement. | J25: =IF(I25="","",MATCH(I25,{"A";"B";"C";"D";"E"},0))
B26: 8.2 | C26: Le reporting relie-t-il indicateurs (KPI/KRI), risques et objectifs ? | D26: L'information n'est communiquée que sur demande ou en cas d'escalade individuelle. | E26: Des indicateurs de base existent pour les processus clés ; les écarts significatifs déclenchent des investigations. | F26: Le reporting est cohérent et relie les indicateurs aux risques et objectifs, avec une qualité de données variable. | G26: Le format est évalué avec les utilisateurs et ajusté à leurs besoins ; des méthodes dédiées mesurent la culture du risque. | H26: Le reporting est personnalisable, permet une analyse détaillée des risques interreliés, et son efficacité est évaluée périodiquement. | J26: =IF(I26="","",MATCH(I26,{"A";"B";"C";"D";"E"},0))
B27: 8.3 | C27: L'information sur les risques parvient-elle aux instances au bon moment pour décider ? | D27: L'information arrive trop tard ou de façon fragmentée pour éclairer une décision. | E27: L'information est disponible à échéance fixe, sans capacité d'escalade rapide hors calendrier. | F27: Un mécanisme d'escalade est défini pour les risques dépassant un seuil, avec des délais convenus. | G27: L'information critique remonte rapidement et de façon fiable, avec un dispositif d'alerte éprouvé. | H27: La remontée est continue et automatisée, permettant une décision quasi immédiate sur les risques majeurs. | J27: =IF(I27="","",MATCH(I27,{"A";"B";"C";"D";"E"},0))
A28: 9. Continuité d'activité (PCA/PRA) | B28: 9.1 | C28: Une analyse d'impact sur l'activité (BIA) est-elle réalisée et maintenue ? | D28: Aucun BIA n'a été réalisé ; les activités critiques ne sont pas formellement identifiées. | E28: Un recensement des activités critiques existe, sans RTO/RPO formalisés ni validation métier. | F28: Un BIA est réalisé pour les processus critiques, avec RTO/RPO définis et validés par les métiers. | G28: Le BIA couvre l'ensemble du périmètre, est revu annuellement et intègre les dépendances (SI, fournisseurs, sites, compétences). | H28: Le BIA est maintenu dynamiquement et ses paramètres sont réévalués automatiquement lors des changements structurants. | J28: =IF(I28="","",MATCH(I28,{"A";"B";"C";"D";"E"},0))
B29: 9.2 | C29: Des stratégies et plans de continuité/reprise (PCA/PRA) sont-ils formalisés ? | D29: Aucun plan formalisé ; la réponse reposerait sur l'improvisation et les personnes présentes. | E29: Des plans partiels existent pour certains domaines (souvent le SI), sans cohérence d'ensemble. | F29: Des PCA/PRA documentés couvrent les activités critiques, avec des stratégies de continuité arbitrées et validées. | G29: Les plans couvrent plusieurs scénarios (indisponibilité SI, site, fournisseur, cyber, énergie) et sont maintenus en condition opérationnelle. | H29: Les plans sont vivants, versionnés, reliés à la cartographie des dépendances et ajustés en continu. | J29: =IF(I29="","",MATCH(I29,{"A";"B";"C";"D";"E"},0))
B30: 9.3 | C30: Les plans sont-ils testés, et les résultats des tests exploités ? | D30: Aucun test n'a été réalisé. | E30: Des tests techniques ponctuels ont lieu (bascule, restauration), sans scénario métier ni RETEX formalisé. | F30: Un programme de tests annuel couvre les plans critiques, avec un RETEX et des actions correctives. | G30: Le programme de tests est pluriannuel et gradué (technique, métier, bout en bout), avec mesure des RTO réellement atteints. | H30: Les tests sont fréquents, parfois inopinés, et leurs résultats alimentent automatiquement la révision des plans et des RTO. | J30: =IF(I30="","",MATCH(I30,{"A";"B";"C";"D";"E"},0))
A31: 10. Gestion de crise (PGC) | B31: 10.1 | C31: Un dispositif de crise (cellule, critères d'activation, chaîne d'alerte) est-il en place ? | D31: Il n'existe pas de dispositif ; la réponse dépendrait des personnes disponibles au moment de l'événement. | E31: Une cellule de crise existe sur le papier, sans critères d'activation clairs ni astreinte organisée. | F31: Le dispositif est formalisé : composition, critères et niveaux d'activation, chaîne d'alerte et moyens de repli documentés. | G31: Le dispositif est gradué par niveau de crise, avec suppléance des rôles, astreinte testée et articulation avec les parties prenantes externes. | H31: Le dispositif est activable en continu, outillé, et son déclenchement peut être suggéré automatiquement par les signaux de surveillance. | J31: =IF(I31="","",MATCH(I31,{"A";"B";"C";"D";"E"},0))
B32: 10.2 | C32: Des exercices de simulation de crise sont-ils conduits ? | D32: Aucun exercice n'a jamais été conduit. | E32: Des exercices ont eu lieu de façon isolée, sur table, sans implication de la direction générale. | F32: Un exercice annuel au moins est conduit sur un scénario réaliste, avec RETEX formalisé. | G32: Un programme d'exercices gradués implique le COMEX et les parties prenantes clés, avec des scénarios variés et évaluation par des observateurs. | H32: Les exercices sont fréquents, parfois inopinés, et leur difficulté est calibrée sur les faiblesses réelles identifiées. | J32: =IF(I32="","",MATCH(I32,{"A";"B";"C";"D";"E"},0))
B33: 10.3 | C33: La conduite de crise est-elle tracée et exploitée (main courante, RETEX, communication) ? | D33: Aucune traçabilité ; les décisions prises en situation ne sont pas consignées. | E33: Une trace partielle existe (messages, comptes rendus), sans main courante structurée ni RETEX systématique. | F33: Une main courante est tenue et un RETEX est produit après chaque activation, avec un plan d'action associé. | G33: Le RETEX est systématique, suivi jusqu'à clôture, et intègre la communication de crise (interne, clients, régulateur, médias). | H33: La traçabilité est outillée en temps réel et alimente automatiquement l'analyse post-crise et l'amélioration du dispositif. | J33: =IF(I33="","",MATCH(I33,{"A";"B";"C";"D";"E"},0))
A34: 11. Résilience organisationnelle | B34: 11.1 | C34: Les dépendances critiques sont-elles cartographiées (fournisseurs, sites, SI, compétences) ? | D34: Les dépendances critiques ne sont pas identifiées de façon structurée. | E34: Certaines dépendances sont connues des équipes concernées, sans cartographie consolidée. | F34: Un référentiel des dépendances critiques existe et est relié aux activités critiques. | G34: Le référentiel couvre les dépendances de rang 2 (fournisseurs de fournisseurs) et alimente les décisions d'achat et d'architecture. | H34: La cartographie est dynamique, alimentée par des données de surveillance, et détecte les concentrations de risque en continu. | J34: =IF(I34="","",MATCH(I34,{"A";"B";"C";"D";"E"},0))
B35: 11.2 | C35: La résilience est-elle intégrée dès la conception des projets, achats et architectures ? | D35: La résilience n'est pas un critère ; elle est traitée après coup, si elle l'est. | E35: La résilience est évoquée dans certains grands projets, sans exigence formelle. | F35: Des exigences de résilience sont intégrées aux jalons projet et aux cahiers des charges d'achat. | G35: La résilience est un critère de décision structurant (architecture, sourcing, implantation), avec arbitrage documenté. | H35: La résilience est conçue nativement dans l'ensemble des choix structurants, avec évaluation quantifiée des gains. | J35: =IF(I35="","",MATCH(I35,{"A";"B";"C";"D";"E"},0))
B36: 11.3 | C36: L'organisation démontre-t-elle sa capacité d'adaptation face aux perturbations réelles ? | D36: Les perturbations passées ont provoqué une désorganisation durable, sans apprentissage. | E36: L'organisation a absorbé des perturbations, essentiellement grâce à l'engagement individuel plutôt qu'au dispositif. | F36: L'organisation a démontré sa capacité à maintenir ses activités critiques lors de perturbations réelles. | G36: La capacité d'adaptation est mesurée (temps de retour à la normale, pertes évitées) et s'améliore d'un événement à l'autre. | H36: L'organisation se réorganise rapidement face à l'inattendu et transforme les perturbations en opportunités d'amélioration structurelle. | J36: =IF(I36="","",MATCH(I36,{"A";"B";"C";"D";"E"},0))
C38: Questions répondues : | I38: =COUNTA(I4:I36)&" / 33" -> 0 / 33

Sheet 2. Résultats
B2: Résultats de l'évaluation
B3: Calcul automatique — aucune saisie requise sur cet onglet.
B5: Dimension | C5: Score /5 | D5: Poids | E5: Contribution | F5: Niveau atteint | G5: Réponses
B6: 1. Stratégie | C6: =IFERROR(AVERAGE('1. Questionnaire'!J4:J6),"") | D6: ='0. Notice'!C37 -> 8 | E6: =IFERROR(C6*D6,"") | F6: =IF(C6="","—",INDEX('0. Notice'!$D$27:$D$31,MATCH(C6,{0;1.81;2.61;3.41;4.21},1))) -> — | G6: =COUNTA('1. Questionnaire'!I4:I6)&" / 3" -> 0 / 3 | P6: =IF(C6="",0,C6*D6) -> 0 | Q6: =IF(C6="",0,D6) -> 0
B7: 2. Gouvernance | C7: =IFERROR(AVERAGE('1. Questionnaire'!J7:J9),"") | D7: ='0. Notice'!C38 -> 12 | E7: =IFERROR(C7*D7,"") | F7: =IF(C7="","—",INDEX('0. Notice'!$D$27:$D$31,MATCH(C7,{0;1.81;2.61;3.41;4.21},1))) -> — | G7: =COUNTA('1. Questionnaire'!I7:I9)&" / 3" -> 0 / 3 | P7: =IF(C7="",0,C7*D7) -> 0 | Q7: =IF(C7="",0,D7) -> 0
B8: 3. Culture | C8: =IFERROR(AVERAGE('1. Questionnaire'!J10:J12),"") | D8: ='0. Notice'!C39 -> 8 | E8: =IFERROR(C8*D8,"") | F8: =IF(C8="","—",INDEX('0. Notice'!$D$27:$D$31,MATCH(C8,{0;1.81;2.61;3.41;4.21},1))) -> — | G8: =COUNTA('1. Questionnaire'!I10:I12)&" / 3" -> 0 / 3 | P8: =IF(C8="",0,C8*D8) -> 0 | Q8: =IF(C8="",0,D8) -> 0
B9: 4. Identification des risques | C9: =IFERROR(AVERAGE('1. Questionnaire'!J13:J15),"") | D9: ='0. Notice'!C40 -> 10 | E9: =IFERROR(C9*D9,"") | F9: =IF(C9="","—",INDEX('0. Notice'!$D$27:$D$31,MATCH(C9,{0;1.81;2.61;3.41;4.21},1))) -> — | G9: =COUNTA('1. Questionnaire'!I13:I15)&" / 3" -> 0 / 3 | P9: =IF(C9="",0,C9*D9) -> 0 | Q9: =IF(C9="",0,D9) -> 0
B10: 5. Analyse et évaluation des risques | C10: =IFERROR(AVERAGE('1. Questionnaire'!J16:J18),"") | D10: ='0. Notice'!C41 -> 10 | E10: =IFERROR(C10*D10,"") | F10: =IF(C10="","—",INDEX('0. Notice'!$D$27:$D$31,MATCH(C10,{0;1.81;2.61;3.41;4.21},1))) -> — | G10: =COUNTA('1. Questionnaire'!I16:I18)&" / 3" -> 0 / 3 | P10: =IF(C10="",0,C10*D10) -> 0 | Q10: =IF(C10="",0,D10) -> 0
B11: 6. Traitement des risques | C11: =IFERROR(AVERAGE('1. Questionnaire'!J19:J21),"") | D11: ='0. Notice'!C42 -> 10 | E11: =IFERROR(C11*D11,"") | F11: =IF(C11="","—",INDEX('0. Notice'!$D$27:$D$31,MATCH(C11,{0;1.81;2.61;3.41;4.21},1))) -> — | G11: =COUNTA('1. Questionnaire'!I19:I21)&" / 3" -> 0 / 3 | P11: =IF(C11="",0,C11*D11) -> 0 | Q11: =IF(C11="",0,D11) -> 0
B12: 7. Revue et révision | C12: =IFERROR(AVERAGE('1. Questionnaire'!J22:J24),"") | D12: ='0. Notice'!C43 -> 7 | E12: =IFERROR(C12*D12,"") | F12: =IF(C12="","—",INDEX('0. Notice'!$D$27:$D$31,MATCH(C12,{0;1.81;2.61;3.41;4.21},1))) -> — | G12: =COUNTA('1. Questionnaire'!I22:I24)&" / 3" -> 0 / 3 | P12: =IF(C12="",0,C12*D12) -> 0 | Q12: =IF(C12="",0,D12) -> 0
B13: 8. Information et reporting | C13: =IFERROR(AVERAGE('1. Questionnaire'!J25:J27),"") | D13: ='0. Notice'!C44 -> 7 | E13: =IFERROR(C13*D13,"") | F13: =IF(C13="","—",INDEX('0. Notice'!$D$27:$D$31,MATCH(C13,{0;1.81;2.61;3.41;4.21},1))) -> — | G13: =COUNTA('1. Questionnaire'!I25:I27)&" / 3" -> 0 / 3 | P13: =IF(C13="",0,C13*D13) -> 0 | Q13: =IF(C13="",0,D13) -> 0
B14: 9. Continuité d'activité (PCA/PRA) | C14: =IFERROR(AVERAGE('1. Questionnaire'!J28:J30),"") | D14: ='0. Notice'!C45 -> 12 | E14: =IFERROR(C14*D14,"") | F14: =IF(C14="","—",INDEX('0. Notice'!$D$27:$D$31,MATCH(C14,{0;1.81;2.61;3.41;4.21},1))) -> — | G14: =COUNTA('1. Questionnaire'!I28:I30)&" / 3" -> 0 / 3 | P14: =IF(C14="",0,C14*D14) -> 0 | Q14: =IF(C14="",0,D14) -> 0
B15: 10. Gestion de crise (PGC) | C15: =IFERROR(AVERAGE('1. Questionnaire'!J31:J33),"") | D15: ='0. Notice'!C46 -> 10 | E15: =IFERROR(C15*D15,"") | F15: =IF(C15="","—",INDEX('0. Notice'!$D$27:$D$31,MATCH(C15,{0;1.81;2.61;3.41;4.21},1))) -> — | G15: =COUNTA('1. Questionnaire'!I31:I33)&" / 3" -> 0 / 3 | P15: =IF(C15="",0,C15*D15) -> 0 | Q15: =IF(C15="",0,D15) -> 0
B16: 11. Résilience organisationnelle | C16: =IFERROR(AVERAGE('1. Questionnaire'!J34:J36),"") | D16: ='0. Notice'!C47 -> 6 | E16: =IFERROR(C16*D16,"") | F16: =IF(C16="","—",INDEX('0. Notice'!$D$27:$D$31,MATCH(C16,{0;1.81;2.61;3.41;4.21},1))) -> — | G16: =COUNTA('1. Questionnaire'!I34:I36)&" / 3" -> 0 / 3 | P16: =IF(C16="",0,C16*D16) -> 0 | Q16: =IF(C16="",0,D16) -> 0
B17: SCORE GLOBAL PONDÉRÉ | C17: =IF(SUM(Q6:Q16)=0,"",SUM(P6:P16)/SUM(Q6:Q16)) | D17: =SUM(D6:D16) -> 100 | F17: =IF(C17="","—",INDEX('0. Notice'!$D$27:$D$31,MATCH(C17,{0;1.81;2.61;3.41;4.21},1))) -> —
B20: Grille d'interprétation
B21: Score moyen | C21: Niveau
B22: 1,00 – 1,80 | C22: Émergent
B23: 1,81 – 2,60 | C23: En progression
B24: 2,61 – 3,40 | C24: Établi
B25: 3,41 – 4,20 | C25: Avancé
B26: 4,21 – 5,00 | C26: Aspirationnel

Sheet 3. Recommandations
A1: Recommandations personnalisées
A2: Généré automatiquement à partir du niveau atteint sur chaque dimension. Traitez en priorité les dimensions dont le score apparaît en rouge ou en orange, en tenant compte de leur poids.
A4: Dimension | B4: Score /5 | C4: Niveau | D4: Diagnostic | E4: Actions court terme (0–6 mois) | F4: Actions moyen terme (6–18 mois)
A5: ='2. Résultats'!B6 -> 1. Stratégie | B5: ='2. Résultats'!C6 | C5: ='2. Résultats'!F6 -> — | D5: =IFERROR(INDEX('4. Référentiel recos'!$D$4:$D$58,MATCH('2. Résultats'!$B$6&"|"&'2. Résultats'!$F$6,'4. Référentiel recos'!$A$4:$A$58,0)),"Complétez le questionnaire pour cette dimension.") -> Complétez le questionnaire pour cette dimension. | E5: =IFERROR(INDEX('4. Référentiel recos'!$E$4:$E$58,MATCH('2. Résultats'!$B$6&"|"&'2. Résultats'!$F$6,'4. Référentiel recos'!$A$4:$A$58,0)),"Complétez le questionnaire pour cette dimension.") -> Complétez le questionnaire pour cette dimension. | F5: =IFERROR(INDEX('4. Référentiel recos'!$F$4:$F$58,MATCH('2. Résultats'!$B$6&"|"&'2. Résultats'!$F$6,'4. Référentiel recos'!$A$4:$A$58,0)),"Complétez le questionnaire pour cette dimension.") -> Complétez le questionnaire pour cette dimension.
A6: ='2. Résultats'!B7 -> 2. Gouvernance | B6: ='2. Résultats'!C7 | C6: ='2. Résultats'!F7 -> — | D6: =IFERROR(INDEX('4. Référentiel recos'!$D$4:$D$58,MATCH('2. Résultats'!$B$7&"|"&'2. Résultats'!$F$7,'4. Référentiel recos'!$A$4:$A$58,0)),"Complétez le questionnaire pour cette dimension.") -> Complétez le questionnaire pour cette dimension. | E6: =IFERROR(INDEX('4. Référentiel recos'!$E$4:$E$58,MATCH('2. Résultats'!$B$7&"|"&'2. Résultats'!$F$7,'4. Référentiel recos'!$A$4:$A$58,0)),"Complétez le questionnaire pour cette dimension.") -> Complétez le questionnaire pour cette dimension. | F6: =IFERROR(INDEX('4. Référentiel recos'!$F$4:$F$58,MATCH('2. Résultats'!$B$7&"|"&'2. Résultats'!$F$7,'4. Référentiel recos'!$A$4:$A$58,0)),"Complétez le questionnaire pour cette dimension.") -> Complétez le questionnaire pour cette dimension.
A7: ='2. Résultats'!B8 -> 3. Culture | B7: ='2. Résultats'!C8 | C7: ='2. Résultats'!F8 -> — | D7: =IFERROR(INDEX('4. Référentiel recos'!$D$4:$D$58,MATCH('2. Résultats'!$B$8&"|"&'2. Résultats'!$F$8,'4. Référentiel recos'!$A$4:$A$58,0)),"Complétez le questionnaire pour cette dimension.") -> Complétez le questionnaire pour cette dimension. | E7: =IFERROR(INDEX('4. Référentiel recos'!$E$4:$E$58,MATCH('2. Résultats'!$B$8&"|"&'2. Résultats'!$F$8,'4. Référentiel recos'!$A$4:$A$58,0)),"Complétez le questionnaire pour cette dimension.") -> Complétez le questionnaire pour cette dimension. | F7: =IFERROR(INDEX('4. Référentiel recos'!$F$4:$F$58,MATCH('2. Résultats'!$B$8&"|"&'2. Résultats'!$F$8,'4. Référentiel recos'!$A$4:$A$58,0)),"Complétez le questionnaire pour cette dimension.") -> Complétez le questionnaire pour cette dimension.
A8: ='2. Résultats'!B9 -> 4. Identification des risques | B8: ='2. Résultats'!C9 | C8: ='2. Résultats'!F9 -> — | D8: =IFERROR(INDEX('4. Référentiel recos'!$D$4:$D$58,MATCH('2. Résultats'!$B$9&"|"&'2. Résultats'!$F$9,'4. Référentiel recos'!$A$4:$A$58,0)),"Complétez le questionnaire pour cette dimension.") -> Complétez le questionnaire pour cette dimension. | E8: =IFERROR(INDEX('4. Référentiel recos'!$E$4:$E$58,MATCH('2. Résultats'!$B$9&"|"&'2. Résultats'!$F$9,'4. Référentiel recos'!$A$4:$A$58,0)),"Complétez le questionnaire pour cette dimension.") -> Complétez le questionnaire pour cette dimension. | F8: =IFERROR(INDEX('4. Référentiel recos'!$F$4:$F$58,MATCH('2. Résultats'!$B$9&"|"&'2. Résultats'!$F$9,'4. Référentiel recos'!$A$4:$A$58,0)),"Complétez le questionnaire pour cette dimension.") -> Complétez le questionnaire pour cette dimension.
A9: ='2. Résultats'!B10 -> 5. Analyse et évaluation des risques | B9: ='2. Résultats'!C10 | C9: ='2. Résultats'!F10 -> — | D9: =IFERROR(INDEX('4. Référentiel recos'!$D$4:$D$58,MATCH('2. Résultats'!$B$10&"|"&'2. Résultats'!$F$10,'4. Référentiel recos'!$A$4:$A$58,0)),"Complétez le questionnaire pour cette dimension.") -> Complétez le questionnaire pour cette dimension. | E9: =IFERROR(INDEX('4. Référentiel recos'!$E$4:$E$58,MATCH('2. Résultats'!$B$10&"|"&'2. Résultats'!$F$10,'4. Référentiel recos'!$A$4:$A$58,0)),"Complétez le questionnaire pour cette dimension.") -> Complétez le questionnaire pour cette dimension. | F9: =IFERROR(INDEX('4. Référentiel recos'!$F$4:$F$58,MATCH('2. Résultats'!$B$10&"|"&'2. Résultats'!$F$10,'4. Référentiel recos'!$A$4:$A$58,0)),"Complétez le questionnaire pour cette dimension.") -> Complétez le questionnaire pour cette dimension.
A10: ='2. Résultats'!B11 -> 6. Traitement des risques | B10: ='2. Résultats'!C11 | C10: ='2. Résultats'!F11 -> — | D10: =IFERROR(INDEX('4. Référentiel recos'!$D$4:$D$58,MATCH('2. Résultats'!$B$11&"|"&'2. Résultats'!$F$11,'4. Référentiel recos'!$A$4:$A$58,0)),"Complétez le questionnaire pour cette dimension.") -> Complétez le questionnaire pour cette dimension. | E10: =IFERROR(INDEX('4. Référentiel recos'!$E$4:$E$58,MATCH('2. Résultats'!$B$11&"|"&'2. Résultats'!$F$11,'4. Référentiel recos'!$A$4:$A$58,0)),"Complétez le questionnaire pour cette dimension.") -> Complétez le questionnaire pour cette dimension. | F10: =IFERROR(INDEX('4. Référentiel recos'!$F$4:$F$58,MATCH('2. Résultats'!$B$11&"|"&'2. Résultats'!$F$11,'4. Référentiel recos'!$A$4:$A$58,0)),"Complétez le questionnaire pour cette dimension.") -> Complétez le questionnaire pour cette dimension.
A11: ='2. Résultats'!B12 -> 7. Revue et révision | B11: ='2. Résultats'!C12 | C11: ='2. Résultats'!F12 -> — | D11: =IFERROR(INDEX('4. Référentiel recos'!$D$4:$D$58,MATCH('2. Résultats'!$B$12&"|"&'2. Résultats'!$F$12,'4. Référentiel recos'!$A$4:$A$58,0)),"Complétez le questionnaire pour cette dimension.") -> Complétez le questionnaire pour cette dimension. | E11: =IFERROR(INDEX('4. Référentiel recos'!$E$4:$E$58,MATCH('2. Résultats'!$B$12&"|"&'2. Résultats'!$F$12,'4. Référentiel recos'!$A$4:$A$58,0)),"Complétez le questionnaire pour cette dimension.") -> Complétez le questionnaire pour cette dimension. | F11: =IFERROR(INDEX('4. Référentiel recos'!$F$4:$F$58,MATCH('2. Résultats'!$B$12&"|"&'2. Résultats'!$F$12,'4. Référentiel recos'!$A$4:$A$58,0)),"Complétez le questionnaire pour cette dimension.") -> Complétez le questionnaire pour cette dimension.
A12: ='2. Résultats'!B13 -> 8. Information et reporting | B12: ='2. Résultats'!C13 | C12: ='2. Résultats'!F13 -> — | D12: =IFERROR(INDEX('4. Référentiel recos'!$D$4:$D$58,MATCH('2. Résultats'!$B$13&"|"&'2. Résultats'!$F$13,'4. Référentiel recos'!$A$4:$A$58,0)),"Complétez le questionnaire pour cette dimension.") -> Complétez le questionnaire pour cette dimension. | E12: =IFERROR(INDEX('4. Référentiel recos'!$E$4:$E$58,MATCH('2. Résultats'!$B$13&"|"&'2. Résultats'!$F$13,'4. Référentiel recos'!$A$4:$A$58,0)),"Complétez le questionnaire pour cette dimension.") -> Complétez le questionnaire pour cette dimension. | F12: =IFERROR(INDEX('4. Référentiel recos'!$F$4:$F$58,MATCH('2. Résultats'!$B$13&"|"&'2. Résultats'!$F$13,'4. Référentiel recos'!$A$4:$A$58,0)),"Complétez le questionnaire pour cette dimension.") -> Complétez le questionnaire pour cette dimension.
A13: ='2. Résultats'!B14 -> 9. Continuité d'activité (PCA/PRA) | B13: ='2. Résultats'!C14 | C13: ='2. Résultats'!F14 -> — | D13: =IFERROR(INDEX('4. Référentiel recos'!$D$4:$D$58,MATCH('2. Résultats'!$B$14&"|"&'2. Résultats'!$F$14,'4. Référentiel recos'!$A$4:$A$58,0)),"Complétez le questionnaire pour cette dimension.") -> Complétez le questionnaire pour cette dimension. | E13: =IFERROR(INDEX('4. Référentiel recos'!$E$4:$E$58,MATCH('2. Résultats'!$B$14&"|"&'2. Résultats'!$F$14,'4. Référentiel recos'!$A$4:$A$58,0)),"Complétez le questionnaire pour cette dimension.") -> Complétez le questionnaire pour cette dimension. | F13: =IFERROR(INDEX('4. Référentiel recos'!$F$4:$F$58,MATCH('2. Résultats'!$B$14&"|"&'2. Résultats'!$F$14,'4. Référentiel recos'!$A$4:$A$58,0)),"Complétez le questionnaire pour cette dimension.") -> Complétez le questionnaire pour cette dimension.
A14: ='2. Résultats'!B15 -> 10. Gestion de crise (PGC) | B14: ='2. Résultats'!C15 | C14: ='2. Résultats'!F15 -> — | D14: =IFERROR(INDEX('4. Référentiel recos'!$D$4:$D$58,MATCH('2. Résultats'!$B$15&"|"&'2. Résultats'!$F$15,'4. Référentiel recos'!$A$4:$A$58,0)),"Complétez le questionnaire pour cette dimension.") -> Complétez le questionnaire pour cette dimension. | E14: =IFERROR(INDEX('4. Référentiel recos'!$E$4:$E$58,MATCH('2. Résultats'!$B$15&"|"&'2. Résultats'!$F$15,'4. Référentiel recos'!$A$4:$A$58,0)),"Complétez le questionnaire pour cette dimension.") -> Complétez le questionnaire pour cette dimension. | F14: =IFERROR(INDEX('4. Référentiel recos'!$F$4:$F$58,MATCH('2. Résultats'!$B$15&"|"&'2. Résultats'!$F$15,'4. Référentiel recos'!$A$4:$A$58,0)),"Complétez le questionnaire pour cette dimension.") -> Complétez le questionnaire pour cette dimension.
A15: ='2. Résultats'!B16 -> 11. Résilience organisationnelle | B15: ='2. Résultats'!C16 | C15: ='2. Résultats'!F16 -> — | D15: =IFERROR(INDEX('4. Référentiel recos'!$D$4:$D$58,MATCH('2. Résultats'!$B$16&"|"&'2. Résultats'!$F$16,'4. Référentiel recos'!$A$4:$A$58,0)),"Complétez le questionnaire pour cette dimension.") -> Complétez le questionnaire pour cette dimension. | E15: =IFERROR(INDEX('4. Référentiel recos'!$E$4:$E$58,MATCH('2. Résultats'!$B$16&"|"&'2. Résultats'!$F$16,'4. Référentiel recos'!$A$4:$A$58,0)),"Complétez le questionnaire pour cette dimension.") -> Complétez le questionnaire pour cette dimension. | F15: =IFERROR(INDEX('4. Référentiel recos'!$F$4:$F$58,MATCH('2. Résultats'!$B$16&"|"&'2. Résultats'!$F$16,'4. Référentiel recos'!$A$4:$A$58,0)),"Complétez le questionnaire pour cette dimension.") -> Complétez le questionnaire pour cette dimension.

Sheet 4. Référentiel recos
A1: Référentiel des recommandations (11 dimensions × 5 niveaux) — onglet technique, ne pas modifier
A3: Clé | B3: Dimension | C3: Niveau | D3: Diagnostic | E3: Actions court terme (0–6 mois) | F3: Actions moyen terme (6–18 mois)
A4: 1. Stratégie|Émergent | B4: 1. Stratégie | C4: Émergent | D4: La stratégie est pilotée sans lecture prospective des risques ; les décisions subissent les événements au lieu de les anticiper. | E4: Introduire un point « principaux risques de mise en œuvre » dans le prochain cycle de planification. Recenser les 10 risques majeurs pouvant compromettre les objectifs de l'année. | F4: Formaliser une première déclaration d'appétit au risque validée par la direction générale et reliée aux objectifs stratégiques.
A5: 1. Stratégie|En progression | B5: 1. Stratégie | C5: En progression | D5: Le lien entre stratégie et risque existe mais reste ponctuel et déconnecté de l'appétit au risque. | E5: Structurer l'analyse des risques stratégiques selon un format unique appliqué à toutes les directions. Relier chaque objectif majeur à ses risques d'atteinte. | F5: Publier une déclaration d'appétit au risque intégrant les arbitrages, et l'utiliser explicitement lors des arbitrages budgétaires.
A6: 1. Stratégie|Établi | B6: 1. Stratégie | C6: Établi | D6: La démarche est en place et cohérente ; le potentiel de progression porte sur la prospective et la granularité de l'appétit au risque. | E6: Mettre en place une revue semestrielle de l'appétit au risque par la gouvernance, à la lumière des événements survenus. | F6: Déployer une veille prospective et des exercices de scénarios impliquant des parties prenantes externes (régulateur, fournisseurs clés, pairs).
A7: 1. Stratégie|Avancé | B7: 1. Stratégie | C7: Avancé | D7: Le dispositif est mature ; l'enjeu devient la finesse et la réactivité des ajustements. | E7: Décliner l'appétit au risque en tolérances chiffrées par domaine et les intégrer aux tableaux de bord de direction. | F7: Automatiser le suivi des indicateurs stratégiques de risque pour raccourcir le délai entre signal et ajustement de trajectoire.
A8: 1. Stratégie|Aspirationnel | B8: 1. Stratégie | C8: Aspirationnel | D8: Niveau de référence. L'enjeu est le maintien dans la durée et le partage de la pratique. | E8: Documenter la démarche pour la pérenniser au-delà des personnes en place. | F8: Se positionner en référence sectorielle et challenger le modèle par des revues externes indépendantes.
A9: 2. Gouvernance|Émergent | B9: 2. Gouvernance | C9: Émergent | D9: L'absence de structure claire empêche toute responsabilisation : les risques n'ont pas de propriétaire et ne sont pas arbitrés. | E9: Désigner un responsable de la gestion des risques et un sponsor au niveau de la direction générale. Établir la liste des instances existantes et de leur rôle réel en matière de risque. | F9: Créer un comité des risques avec mandat écrit, fréquence de réunion et ordre du jour type.
A10: 2. Gouvernance|En progression | B10: 2. Gouvernance | C10: En progression | D10: Une gouvernance existe mais reste cloisonnée : l'information circule mal entre instances et la responsabilité est partielle. | E10: Formaliser un mandat écrit pour chaque instance et supprimer les zones de recouvrement. Instaurer un reporting périodique standard au comité de direction. | F10: Déployer une matrice RACI des risques par direction et clarifier l'articulation entre métiers, fonction risque et audit.
A11: 2. Gouvernance|Établi | B11: 2. Gouvernance | C11: Établi | D11: La gouvernance est structurée et fonctionne ; les marges portent sur la profondeur des arbitrages et la coordination des lignes de défense. | E11: Faire approuver formellement les tolérances au risque pour les risques majeurs par l'instance transverse. | F11: Construire un plan d'assurance coordonné entre fonction risque, conformité et audit pour éliminer les angles morts et les doublons.
A12: 2. Gouvernance|Avancé | B12: 2. Gouvernance | C12: Avancé | D12: Gouvernance solide. L'enjeu est la vérification indépendante de son efficacité réelle. | E12: Soumettre le dispositif à une évaluation indépendante (audit interne ou externe) sur son efficacité, pas seulement sa conformité. | F12: Développer la capacité de décision rapide hors calendrier pour les risques à cinétique courte.
A13: 2. Gouvernance|Aspirationnel | B13: 2. Gouvernance | C13: Aspirationnel | D13: Niveau de référence. Le risque principal devient la complaisance. | E13: Maintenir la cadence des évaluations indépendantes et faire challenger la gouvernance par des regards externes. | F13: Partager la pratique et tester le dispositif sur des scénarios inédits pour éviter l'auto-satisfaction.
A14: 3. Culture|Émergent | B14: 3. Culture | C14: Émergent | D14: La gestion des risques est perçue comme une contrainte administrative ; les alertes ne remontent pas. | E14: Faire porter un message explicite par la direction générale sur l'attendu en matière de risque. Créer un canal de remontée d'alerte identifié et communiqué. | F14: Déployer une sensibilisation de base à l'ensemble de l'encadrement, avec des cas concrets issus de l'entreprise.
... A58: 11. Résilience organisationnelle|Aspirationnel | B58: 11. Résilience organisationnelle | C58: Aspirationnel | D58: Niveau de référence. | E58: Vérifier que la résilience conçue tient face à des perturbations non anticipées par les modèles. | F58: Préserver les marges de manœuvre (redondances, stocks, polyvalence) que l'optimisation économique tend à éroder.
